ecsbatchcli/__init__.py
ecsbatchcli/api_client.py
ecsbatchcli/cli.py
ecsbatchcli/config.py
ecsbatchcli/error_handler.py
ecsbatchcli/logger.py
ecsbatchcli/operations.py
ecsbatchcli/output.py
ecsbatchcli/rate_limiter.py
ecsbatchcli/sdk_adapter.py
ecsbatchcli-0.1.3.dist-info/LICENSE
ecsbatchcli-0.1.3.dist-info/METADATA
ecsbatchcli-0.1.3.dist-info/WHEEL
ecsbatchcli-0.1.3.dist-info/entry_points.txt
ecsbatchcli-0.1.3.dist-info/top_level.txt
ecsbatchcli-0.1.3.dist-info/RECORD
