Metadata-Version: 2.1
Name: ecsbatchcli
Version: 0.1.3
Summary: A CLI tool for batch management of Volcano Engine ECS instances
Home-page: https://github.com/volcengine/ecsbatchcli
Author: Volcano Engine Team
Author-email: support@volcengine.com
Classifier: Development Status :: 3 - Alpha
Classifier: Intended Audience :: Developers
Classifier: Intended Audience :: System Administrators
Classifier: License :: OSI Approved :: MIT License
Classifier: Programming Language :: Python :: 3
Classifier: Programming Language :: Python :: 3.6
Classifier: Programming Language :: Python :: 3.7
Classifier: Programming Language :: Python :: 3.8
Classifier: Programming Language :: Python :: 3.9
Classifier: Topic :: System :: Systems Administration
Requires-Python: >=3.6
License-File: LICENSE
Requires-Dist: pyyaml>=6.0
Requires-Dist: tqdm>=4.64.0
Requires-Dist: colorama>=0.4.4
